codebox/__init__.py
codebox/dict_tools.py
codebox/dir_tools.py
codebox/file_tools.py
codebox/yaml_tools.py
codebox-1.1.0.dist-info/LICENSE.txt
codebox-1.1.0.dist-info/WHEEL
codebox-1.1.0.dist-info/METADATA
codebox-1.1.0.dist-info/RECORD
